{
    "name": "dp2_level1_state",
    "mineral": 175.0,
    "Pylons": 0.0,
    "BOT Marines": 0.0,
    "TOP Marines": 0.0,
    "BOT Banelings": 1.0,
    "TOP Banelings": 0.0,
    "BOT Immortals": 0.0,
    "TOP Immortals": 0.0,
    "state": [
        175.0,
        0.0,
        0.0,
        0.0,
        0.0,
        1.0,
        0.0,
        0.0,
        2.0,
        0.0,
        0.0,
        0.0,
        0.0,
        0.0,
        0.0,
        0.0,
        0.0,
        0.0,
        0.0,
        1.0,
        0.0,
        2.0,
        0.0,
        0.0,
        0.0,
        0.0,
        0.0,
        2000.0,
        2000.0,
        2000.0,
        2000.0,
        2.0
    ],
    "action": null,
    "best q_value": 0.7643871903419495,
    "after state q_value": null,
    "tree path": "",
    "children": [
        [
            {
                "name": "dp2_level1_action_max_0(best)_0(best)",
                "mineral": 0.0,
                "Pylons": 0.0,
                "BOT Marines": 0.0,
                "TOP Marines": 2.0,
                "BOT Banelings": 1.0,
                "TOP Banelings": 1.0,
                "BOT Immortals": 0.0,
                "TOP Immortals": 0.0,
                "state": [
                    0.0,
                    2.0,
                    1.0,
                    0.0,
                    0.0,
                    1.0,
                    0.0,
                    0.0,
                    2.0,
                    0.0,
                    0.0,
                    0.0,
                    0.0,
                    0.0,
                    0.0,
                    0.0,
                    0.0,
                    0.0,
                    0.0,
                    1.0,
                    0.0,
                    2.0,
                    0.0,
                    0.0,
                    0.0,
                    0.0,
                    0.0,
                    2000.0,
                    2000.0,
                    2000.0,
                    2000.0,
                    2.0
                ],
                "action": "2100000",
                "best q_value": 0.7643871903419495,
                "after state q_value": 0.8114104866981506,
                "tree path": "0",
                "children": [
                    [
                        {
                            "name": "dp2_level1_action_min_00_00",
                            "mineral": 175.0,
                            "Pylons": 0.0,
                            "BOT Marines": 0.0,
                            "TOP Marines": 0.0,
                            "BOT Banelings": 1.0,
                            "TOP Banelings": 0.0,
                            "BOT Immortals": 0.0,
                            "TOP Immortals": 0.0,
                            "state": [
                                175.0,
                                0.0,
                                0.0,
                                0.0,
                                0.0,
                                1.0,
                                0.0,
                                0.0,
                                2.0,
                                0.0,
                                0.0,
                                0.0,
                                2.0,
                                0.0,
                                0.0,
                                0.0,
                                0.0,
                                0.0,
                                0.0,
                                1.0,
                                0.0,
                                2.0,
                                0.0,
                                0.0,
                                0.0,
                                0.0,
                                0.0,
                                2000.0,
                                2000.0,
                                2000.0,
                                2000.0,
                                2.0
                            ],
                            "action": "0000200",
                            "best q_value": 0.7651481032371521,
                            "after state q_value": 0.8106204867362976,
                            "tree path": "00",
                            "children": [
                                []
                            ]
                        },
                        {
                            "name": "dp2_level1_action_min_01(best)_01(best)",
                            "mineral": 175.0,
                            "Pylons": 0.0,
                            "BOT Marines": 0.0,
                            "TOP Marines": 0.0,
                            "BOT Banelings": 1.0,
                            "TOP Banelings": 0.0,
                            "BOT Immortals": 0.0,
                            "TOP Immortals": 0.0,
                            "state": [
                                175.0,
                                0.0,
                                0.0,
                                0.0,
                                0.0,
                                1.0,
                                0.0,
                                0.0,
                                2.0,
                                0.0,
                                0.0,
                                1.0,
                                1.0,
                                0.0,
                                0.0,
                                0.0,
                                0.0,
                                0.0,
                                0.0,
                                1.0,
                                0.0,
                                2.0,
                                0.0,
                                0.0,
                                0.0,
                                0.0,
                                0.0,
                                2000.0,
                                2000.0,
                                2000.0,
                                2000.0,
                                2.0
                            ],
                            "action": "0001100",
                            "best q_value": 0.7643871903419495,
                            "after state q_value": 0.7722641229629517,
                            "tree path": "01",
                            "children": [
                                [
                                    {
                                        "name": "dp3_level2_state_010(best)_010(best)",
                                        "mineral": 100.0,
                                        "Pylons": 0.0,
                                        "BOT Marines": 0.0,
                                        "TOP Marines": 2.0,
                                        "BOT Banelings": 1.0,
                                        "TOP Banelings": 1.0,
                                        "BOT Immortals": 0.0,
                                        "TOP Immortals": 0.0,
                                        "state": [
                                            100.0,
                                            2.0,
                                            1.0,
                                            0.0,
                                            0.0,
                                            1.0,
                                            0.0,
                                            0.0,
                                            2.0,
                                            0.0,
                                            0.0,
                                            1.0,
                                            1.0,
                                            0.0,
                                            0.0,
                                            1.0,
                                            -0.0,
                                            -0.0,
                                            0.0,
                                            0.0,
                                            -0.0,
                                            1.0,
                                            -0.0,
                                            0.0,
                                            -0.0,
                                            -0.0,
                                            -0.0,
                                            1997.2222900390625,
                                            2000.1439208984375,
                                            1996.2354736328125,
                                            1987.939697265625,
                                            3.0
                                        ],
                                        "action": null,
                                        "best q_value": 0.7643871903419495,
                                        "after state q_value": null,
                                        "tree path": "010",
                                        "children": [
                                            [
                                                {
                                                    "name": "dp3_level2_action_max_0100_0100",
                                                    "mineral": 0.0,
                                                    "Pylons": 0.0,
                                                    "BOT Marines": 2.0,
                                                    "TOP Marines": 2.0,
                                                    "BOT Banelings": 1.0,
                                                    "TOP Banelings": 1.0,
                                                    "BOT Immortals": 0.0,
                                                    "TOP Immortals": 0.0,
                                                    "state": [
                                                        0.0,
                                                        2.0,
                                                        1.0,
                                                        0.0,
                                                        2.0,
                                                        1.0,
                                                        0.0,
                                                        0.0,
                                                        2.0,
                                                        0.0,
                                                        0.0,
                                                        1.0,
                                                        1.0,
                                                        0.0,
                                                        0.0,
                                                        1.0,
                                                        -0.0,
                                                        -0.0,
                                                        0.0,
                                                        0.0,
                                                        -0.0,
                                                        1.0,
                                                        -0.0,
                                                        0.0,
                                                        -0.0,
                                                        -0.0,
                                                        -0.0,
                                                        1997.2222900390625,
                                                        2000.1439208984375,
                                                        1996.2354736328125,
                                                        1987.939697265625,
                                                        3.0
                                                    ],
                                                    "action": "0002000",
                                                    "best q_value": 0.7234917283058167,
                                                    "after state q_value": 0.8018559217453003,
                                                    "tree path": "0100",
                                                    "children": [
                                                        []
                                                    ]
                                                },
                                                {
                                                    "name": "dp3_level2_action_max_0101_0101",
                                                    "mineral": 25.0,
                                                    "Pylons": 0.0,
                                                    "BOT Marines": 0.0,
                                                    "TOP Marines": 2.0,
                                                    "BOT Banelings": 2.0,
                                                    "TOP Banelings": 1.0,
                                                    "BOT Immortals": 0.0,
                                                    "TOP Immortals": 0.0,
                                                    "state": [
                                                        25.0,
                                                        2.0,
                                                        1.0,
                                                        0.0,
                                                        0.0,
                                                        2.0,
                                                        0.0,
                                                        0.0,
                                                        2.0,
                                                        0.0,
                                                        0.0,
                                                        1.0,
                                                        1.0,
                                                        0.0,
                                                        0.0,
                                                        1.0,
                                                        -0.0,
                                                        -0.0,
                                                        0.0,
                                                        0.0,
                                                        -0.0,
                                                        1.0,
                                                        -0.0,
                                                        0.0,
                                                        -0.0,
                                                        -0.0,
                                                        -0.0,
                                                        1997.2222900390625,
                                                        2000.1439208984375,
                                                        1996.2354736328125,
                                                        1987.939697265625,
                                                        3.0
                                                    ],
                                                    "action": "0000100",
                                                    "best q_value": 0.6756840944290161,
                                                    "after state q_value": 0.7260075807571411,
                                                    "tree path": "0101",
                                                    "children": [
                                                        []
                                                    ]
                                                },
                                                {
                                                    "name": "dp3_level2_action_max_0102(best)_0102(best)",
                                                    "mineral": 0.0,
                                                    "Pylons": 0.0,
                                                    "BOT Marines": 0.0,
                                                    "TOP Marines": 4.0,
                                                    "BOT Banelings": 1.0,
                                                    "TOP Banelings": 1.0,
                                                    "BOT Immortals": 0.0,
                                                    "TOP Immortals": 0.0,
                                                    "state": [
                                                        0.0,
                                                        4.0,
                                                        1.0,
                                                        0.0,
                                                        0.0,
                                                        1.0,
                                                        0.0,
                                                        0.0,
                                                        2.0,
                                                        0.0,
                                                        0.0,
                                                        1.0,
                                                        1.0,
                                                        0.0,
                                                        0.0,
                                                        1.0,
                                                        -0.0,
                                                        -0.0,
                                                        0.0,
                                                        0.0,
                                                        -0.0,
                                                        1.0,
                                                        -0.0,
                                                        0.0,
                                                        -0.0,
                                                        -0.0,
                                                        -0.0,
                                                        1997.2222900390625,
                                                        2000.1439208984375,
                                                        1996.2354736328125,
                                                        1987.939697265625,
                                                        3.0
                                                    ],
                                                    "action": "2000000",
                                                    "best q_value": 0.7643871903419495,
                                                    "after state q_value": 0.7155175805091858,
                                                    "tree path": "0102",
                                                    "children": [
                                                        [
                                                            {
                                                                "name": "dp3_level2_action_min_01020_01020",
                                                                "mineral": 100.0,
                                                                "Pylons": 0.0,
                                                                "BOT Marines": 0.0,
                                                                "TOP Marines": 2.0,
                                                                "BOT Banelings": 1.0,
                                                                "TOP Banelings": 1.0,
                                                                "BOT Immortals": 0.0,
                                                                "TOP Immortals": 0.0,
                                                                "state": [
                                                                    100.0,
                                                                    2.0,
                                                                    1.0,
                                                                    0.0,
                                                                    0.0,
                                                                    1.0,
                                                                    0.0,
                                                                    0.0,
                                                                    3.0,
                                                                    1.0,
                                                                    0.0,
                                                                    1.0,
                                                                    1.0,
                                                                    0.0,
                                                                    0.0,
                                                                    1.0,
                                                                    -0.0,
                                                                    -0.0,
                                                                    0.0,
                                                                    0.0,
                                                                    -0.0,
                                                                    1.0,
                                                                    -0.0,
                                                                    0.0,
                                                                    -0.0,
                                                                    -0.0,
                                                                    -0.0,
                                                                    1997.2222900390625,
                                                                    2000.1439208984375,
                                                                    1996.2354736328125,
                                                                    1987.939697265625,
                                                                    3.0
                                                                ],
                                                                "action": "1100000",
                                                                "best q_value": 0.8175117373466492,
                                                                "after state q_value": 0.7541720271110535,
                                                                "tree path": "01020",
                                                                "children": [
                                                                    []
                                                                ]
                                                            },
                                                            {
                                                                "name": "dp3_level2_action_min_01021_01021",
                                                                "mineral": 100.0,
                                                                "Pylons": 0.0,
                                                                "BOT Marines": 0.0,
                                                                "TOP Marines": 2.0,
                                                                "BOT Banelings": 1.0,
                                                                "TOP Banelings": 1.0,
                                                                "BOT Immortals": 0.0,
                                                                "TOP Immortals": 0.0,
                                                                "state": [
                                                                    100.0,
                                                                    2.0,
                                                                    1.0,
                                                                    0.0,
                                                                    0.0,
                                                                    1.0,
                                                                    0.0,
                                                                    0.0,
                                                                    3.0,
                                                                    0.0,
                                                                    0.0,
                                                                    1.0,
                                                                    1.0,
                                                                    0.0,
                                                                    0.0,
                                                                    1.0,
                                                                    -0.0,
                                                                    -0.0,
                                                                    0.0,
                                                                    0.0,
                                                                    -0.0,
                                                                    1.0,
                                                                    -0.0,
                                                                    0.0,
                                                                    -0.0,
                                                                    -0.0,
                                                                    -0.0,
                                                                    1997.2222900390625,
                                                                    2000.1439208984375,
                                                                    1996.2354736328125,
                                                                    1987.939697265625,
                                                                    3.0
                                                                ],
                                                                "action": "1000000",
                                                                "best q_value": 0.8195069432258606,
                                                                "after state q_value": 0.7348505854606628,
                                                                "tree path": "01021",
                                                                "children": [
                                                                    []
                                                                ]
                                                            },
                                                            {
                                                                "name": "dp3_level2_action_min_01022_01022",
                                                                "mineral": 100.0,
                                                                "Pylons": 0.0,
                                                                "BOT Marines": 0.0,
                                                                "TOP Marines": 2.0,
                                                                "BOT Banelings": 1.0,
                                                                "TOP Banelings": 1.0,
                                                                "BOT Immortals": 0.0,
                                                                "TOP Immortals": 0.0,
                                                                "state": [
                                                                    100.0,
                                                                    2.0,
                                                                    1.0,
                                                                    0.0,
                                                                    0.0,
                                                                    1.0,
                                                                    0.0,
                                                                    0.0,
                                                                    2.0,
                                                                    0.0,
                                                                    0.0,
                                                                    2.0,
                                                                    1.0,
                                                                    0.0,
                                                                    0.0,
                                                                    1.0,
                                                                    -0.0,
                                                                    -0.0,
                                                                    0.0,
                                                                    0.0,
                                                                    -0.0,
                                                                    1.0,
                                                                    -0.0,
                                                                    0.0,
                                                                    -0.0,
                                                                    -0.0,
                                                                    -0.0,
                                                                    1997.2222900390625,
                                                                    2000.1439208984375,
                                                                    1996.2354736328125,
                                                                    1987.939697265625,
                                                                    3.0
                                                                ],
                                                                "action": "0001000",
                                                                "best q_value": 0.8162984848022461,
                                                                "after state q_value": 0.7333052754402161,
                                                                "tree path": "01022",
                                                                "children": [
                                                                    []
                                                                ]
                                                            },
                                                            {
                                                                "name": "dp3_level2_action_min_01023(best)_01023(best)",
                                                                "mineral": 100.0,
                                                                "Pylons": 0.0,
                                                                "BOT Marines": 0.0,
                                                                "TOP Marines": 2.0,
                                                                "BOT Banelings": 1.0,
                                                                "TOP Banelings": 1.0,
                                                                "BOT Immortals": 0.0,
                                                                "TOP Immortals": 0.0,
                                                                "state": [
                                                                    100.0,
                                                                    2.0,
                                                                    1.0,
                                                                    0.0,
                                                                    0.0,
                                                                    1.0,
                                                                    0.0,
                                                                    0.0,
                                                                    2.0,
                                                                    0.0,
                                                                    0.0,
                                                                    1.0,
                                                                    2.0,
                                                                    0.0,
                                                                    0.0,
                                                                    1.0,
                                                                    -0.0,
                                                                    -0.0,
                                                                    0.0,
                                                                    0.0,
                                                                    -0.0,
                                                                    1.0,
                                                                    -0.0,
                                                                    0.0,
                                                                    -0.0,
                                                                    -0.0,
                                                                    -0.0,
                                                                    1997.2222900390625,
                                                                    2000.1439208984375,
                                                                    1996.2354736328125,
                                                                    1987.939697265625,
                                                                    3.0
                                                                ],
                                                                "action": "0000100",
                                                                "best q_value": 0.7643871903419495,
                                                                "after state q_value": 0.713680624961853,
                                                                "tree path": "01023",
                                                                "children": [
                                                                    [
                                                                        {
                                                                            "name": "dp3_level2_state_010230(best)_010230(best)",
                                                                            "mineral": 100.0,
                                                                            "Pylons": 0.0,
                                                                            "BOT Marines": 0.0,
                                                                            "TOP Marines": 4.0,
                                                                            "BOT Banelings": 1.0,
                                                                            "TOP Banelings": 1.0,
                                                                            "BOT Immortals": 0.0,
                                                                            "TOP Immortals": 0.0,
                                                                            "state": [
                                                                                100.0,
                                                                                4.0,
                                                                                1.0,
                                                                                0.0,
                                                                                0.0,
                                                                                1.0,
                                                                                0.0,
                                                                                0.0,
                                                                                2.0,
                                                                                0.0,
                                                                                0.0,
                                                                                1.0,
                                                                                2.0,
                                                                                0.0,
                                                                                0.0,
                                                                                4.0,
                                                                                0.0,
                                                                                -0.0,
                                                                                0.0,
                                                                                -0.0,
                                                                                -0.0,
                                                                                -0.0,
                                                                                -0.0,
                                                                                0.0,
                                                                                1.0,
                                                                                1.0,
                                                                                0.0,
                                                                                1995.7630615234375,
                                                                                1996.0628662109375,
                                                                                1993.5396728515625,
                                                                                1995.337158203125,
                                                                                4.0
                                                                            ],
                                                                            "action": null,
                                                                            "best q_value": 0.7643871903419495,
                                                                            "after state q_value": null,
                                                                            "tree path": "010230",
                                                                            "children": [
                                                                                []
                                                                            ]
                                                                        }
                                                                    ]
                                                                ]
                                                            }
                                                        ]
                                                    ]
                                                },
                                                {
                                                    "name": "dp3_level2_action_max_0103_0103",
                                                    "mineral": 50.0,
                                                    "Pylons": 0.0,
                                                    "BOT Marines": 1.0,
                                                    "TOP Marines": 2.0,
                                                    "BOT Banelings": 1.0,
                                                    "TOP Banelings": 1.0,
                                                    "BOT Immortals": 0.0,
                                                    "TOP Immortals": 0.0,
                                                    "state": [
                                                        50.0,
                                                        2.0,
                                                        1.0,
                                                        0.0,
                                                        1.0,
                                                        1.0,
                                                        0.0,
                                                        0.0,
                                                        2.0,
                                                        0.0,
                                                        0.0,
                                                        1.0,
                                                        1.0,
                                                        0.0,
                                                        0.0,
                                                        1.0,
                                                        -0.0,
                                                        -0.0,
                                                        0.0,
                                                        0.0,
                                                        -0.0,
                                                        1.0,
                                                        -0.0,
                                                        0.0,
                                                        -0.0,
                                                        -0.0,
                                                        -0.0,
                                                        1997.2222900390625,
                                                        2000.1439208984375,
                                                        1996.2354736328125,
                                                        1987.939697265625,
                                                        3.0
                                                    ],
                                                    "action": "0001000",
                                                    "best q_value": 0.7260000705718994,
                                                    "after state q_value": 0.6997741460800171,
                                                    "tree path": "0103",
                                                    "children": [
                                                        []
                                                    ]
                                                }
                                            ]
                                        ]
                                    }
                                ]
                            ]
                        },
                        {
                            "name": "dp2_level1_action_min_02_02",
                            "mineral": 175.0,
                            "Pylons": 0.0,
                            "BOT Marines": 0.0,
                            "TOP Marines": 0.0,
                            "BOT Banelings": 1.0,
                            "TOP Banelings": 0.0,
                            "BOT Immortals": 0.0,
                            "TOP Immortals": 0.0,
                            "state": [
                                175.0,
                                0.0,
                                0.0,
                                0.0,
                                0.0,
                                1.0,
                                0.0,
                                0.0,
                                5.0,
                                0.0,
                                0.0,
                                0.0,
                                0.0,
                                0.0,
                                0.0,
                                0.0,
                                0.0,
                                0.0,
                                0.0,
                                1.0,
                                0.0,
                                2.0,
                                0.0,
                                0.0,
                                0.0,
                                0.0,
                                0.0,
                                2000.0,
                                2000.0,
                                2000.0,
                                2000.0,
                                2.0
                            ],
                            "action": "3000000",
                            "best q_value": 0.8428564667701721,
                            "after state q_value": 0.747218906879425,
                            "tree path": "02",
                            "children": [
                                []
                            ]
                        },
                        {
                            "name": "dp2_level1_action_min_03_03",
                            "mineral": 175.0,
                            "Pylons": 0.0,
                            "BOT Marines": 0.0,
                            "TOP Marines": 0.0,
                            "BOT Banelings": 1.0,
                            "TOP Banelings": 0.0,
                            "BOT Immortals": 0.0,
                            "TOP Immortals": 0.0,
                            "state": [
                                175.0,
                                0.0,
                                0.0,
                                0.0,
                                0.0,
                                1.0,
                                0.0,
                                0.0,
                                2.0,
                                0.0,
                                0.0,
                                0.0,
                                1.0,
                                0.0,
                                0.0,
                                0.0,
                                0.0,
                                0.0,
                                0.0,
                                1.0,
                                0.0,
                                2.0,
                                0.0,
                                0.0,
                                0.0,
                                0.0,
                                0.0,
                                2000.0,
                                2000.0,
                                2000.0,
                                2000.0,
                                2.0
                            ],
                            "action": "0000100",
                            "best q_value": 0.7989338636398315,
                            "after state q_value": 0.7302367091178894,
                            "tree path": "03",
                            "children": [
                                []
                            ]
                        }
                    ]
                ]
            },
            {
                "name": "dp2_level1_action_max_1_1",
                "mineral": 75.0,
                "Pylons": 0.0,
                "BOT Marines": 0.0,
                "TOP Marines": 2.0,
                "BOT Banelings": 1.0,
                "TOP Banelings": 0.0,
                "BOT Immortals": 0.0,
                "TOP Immortals": 0.0,
                "state": [
                    75.0,
                    2.0,
                    0.0,
                    0.0,
                    0.0,
                    1.0,
                    0.0,
                    0.0,
                    2.0,
                    0.0,
                    0.0,
                    0.0,
                    0.0,
                    0.0,
                    0.0,
                    0.0,
                    0.0,
                    0.0,
                    0.0,
                    1.0,
                    0.0,
                    2.0,
                    0.0,
                    0.0,
                    0.0,
                    0.0,
                    0.0,
                    2000.0,
                    2000.0,
                    2000.0,
                    2000.0,
                    2.0
                ],
                "action": "2000000",
                "best q_value": 0.7512489557266235,
                "after state q_value": 0.8017808198928833,
                "tree path": "1",
                "children": [
                    []
                ]
            },
            {
                "name": "dp2_level1_action_max_2_2",
                "mineral": 25.0,
                "Pylons": 0.0,
                "BOT Marines": 0.0,
                "TOP Marines": 0.0,
                "BOT Banelings": 1.0,
                "TOP Banelings": 2.0,
                "BOT Immortals": 0.0,
                "TOP Immortals": 0.0,
                "state": [
                    25.0,
                    0.0,
                    2.0,
                    0.0,
                    0.0,
                    1.0,
                    0.0,
                    0.0,
                    2.0,
                    0.0,
                    0.0,
                    0.0,
                    0.0,
                    0.0,
                    0.0,
                    0.0,
                    0.0,
                    0.0,
                    0.0,
                    1.0,
                    0.0,
                    2.0,
                    0.0,
                    0.0,
                    0.0,
                    0.0,
                    0.0,
                    2000.0,
                    2000.0,
                    2000.0,
                    2000.0,
                    2.0
                ],
                "action": "0200000",
                "best q_value": 0.5932252407073975,
                "after state q_value": 0.7940008044242859,
                "tree path": "2",
                "children": [
                    []
                ]
            },
            {
                "name": "dp2_level1_action_max_3_3",
                "mineral": 25.0,
                "Pylons": 0.0,
                "BOT Marines": 0.0,
                "TOP Marines": 3.0,
                "BOT Banelings": 1.0,
                "TOP Banelings": 0.0,
                "BOT Immortals": 0.0,
                "TOP Immortals": 0.0,
                "state": [
                    25.0,
                    3.0,
                    0.0,
                    0.0,
                    0.0,
                    1.0,
                    0.0,
                    0.0,
                    2.0,
                    0.0,
                    0.0,
                    0.0,
                    0.0,
                    0.0,
                    0.0,
                    0.0,
                    0.0,
                    0.0,
                    0.0,
                    1.0,
                    0.0,
                    2.0,
                    0.0,
                    0.0,
                    0.0,
                    0.0,
                    0.0,
                    2000.0,
                    2000.0,
                    2000.0,
                    2000.0,
                    2.0
                ],
                "action": "3000000",
                "best q_value": 0.7526331543922424,
                "after state q_value": 0.7891325354576111,
                "tree path": "3",
                "children": [
                    []
                ]
            }
        ]
    ]
}